pynudger-0.2.2.dist-info/METADATA
pynudger-0.2.2.dist-info/WHEEL
pynudger-0.2.2.dist-info/entry_points.txt
pynudger/__init__.py
pynudger/__main__.py
pynudger/_check.py
pynudger/_cli.py
pynudger/_loader.py
pynudger/_rule.py
pynudger/py.typed
pynudger/py.typed.license
pynudger-0.2.2.dist-info/RECORD
