Metadata-Version: 2.4
Name: pynudger
Version: 0.2.2
Summary: opennudge Python linter (naming conventions and other automated checks)
Author: open-nudge
Maintainer: open-nudge
License-Expression: Apache-2.0
Classifier: Development Status :: 2 - Pre-Alpha
Classifier: Intended Audience :: Developers
Classifier: Programming Language :: Python
Classifier: Programming Language :: Python :: 3 :: Only
Classifier: Programming Language :: Python :: 3.11
Classifier: Programming Language :: Python :: 3.12
Classifier: Programming Language :: Python :: 3.13
Classifier: Topic :: Software Development :: Libraries
Classifier: Topic :: Software Development :: Libraries :: Python Modules
Classifier: Typing :: Typed
Project-URL: Changelog, https://github.com/open-nudge/pynudger/blob/master/CHANGELOG.md
Project-URL: Documentation, https://open-nudge.github.io/pynudger
Project-URL: Homepage, https://open-nudge.github.io/pynudger
Project-URL: Issues, https://github.com/open-nudge/pynudger/issues
Project-URL: Repository, https://github.com/open-nudge/pynudger
Requires-Python: >=3.11
Requires-Dist: lintkit[rich]>=1
Requires-Dist: loadfig>=0.1.0
